duc193test/__init__.py
duc193test-0.1.dist-info/METADATA
duc193test-0.1.dist-info/WHEEL
duc193test-0.1.dist-info/top_level.txt
duc193test-0.1.dist-info/RECORD
