Metadata-Version: 2.1
Name: duc193test
Version: 0.1
Summary: Thư viện test của duc193
Author: duc193
